{
  "generated_at": "2026-05-27T16:47:31.669Z",
  "summary": {
    "total_items": 8,
    "p0_count": 1,
    "p1_count": 1,
    "requires_human_review_count": 8
  },
  "items": [
    {
      "item_id": "item_1",
      "classification": "new_referral",
      "urgency": "P2",
      "requires_human_review": true,
      "extracted_intake": {
        "child_name": "Emma Lee",
        "dob_or_age": "2018-09-04",
        "parent_contact": "Daniel Lee, 555-0101, daniel.lee@example.com",
        "discipline": [
          "SLP"
        ],
        "diagnosis_or_concern": "Articulation delay and reduced intelligibility",
        "payer": "Blue Cross Blue Shield PPO",
        "member_id": "BCBS-884200"
      },
      "missing_info": [
        "New patient intake forms not yet sent or completed",
        "Prior authorization not yet obtained (auth_required=true per billing system — billing team tasked)"
      ],
      "recommended_next_action": "Intake team should call Daniel Lee today to introduce Cedar Kids, send new patient paperwork, and coordinate with billing to confirm prior auth before converting the pending slot hold (Maya Chen, Thu May 1 at 3:30 PM) into a confirmed appointment.",
      "draft_reply": "Dear Daniel,\n\nThank you for reaching out to Cedar Kids Therapy! We received the referral from Dr. Priya Nair at Northside Pediatrics for Emma's speech-language evaluation and we're excited to welcome her.\n\nWe have a potential appointment opening on Thursday, May 1st at 3:30 PM with Maya Chen, MS CCC-SLP, which aligns with your after-school Tuesday/Thursday preference. Our team is reviewing availability and insurance details — please note this is not yet a confirmed appointment.\n\nA member of our intake team will contact you shortly at 555-0101 to confirm the appointment, review insurance (Blue Cross Blue Shield PPO), and send over new patient paperwork.\n\nIf you have any questions in the meantime, please don't hesitate to reach us by phone or through our patient portal.\n\nWarm regards,\nCedar Kids Therapy",
      "task_ids": [
        "task_01ksn58rycm8h7yzqk2v47acg9",
        "task_01ksn594v73sg1jkmcfavqhr11"
      ],
      "escalation": null,
      "decision_rationale": "This is a complete, clean new SLP referral for a new patient (no existing record found). Insurance was verified as active in-network (BCBS PPO), but the billing system flagged prior authorization as required, so a billing task was created before the slot can be confirmed. A pending-review hold was placed on the best-matching slot (Thu May 1, 3:30 PM, after-school, with Maya Chen) per scheduling policy; no appointment was booked. Urgency is standard P2 — no safeguarding concerns, no same-day operational issues.",
      "tools_called": [
        {
          "call_id": "01KSN58D6DTCV0EVW4KV1RVDNG",
          "name": "search_patient",
          "args": {
            "dob": "2018-09-04",
            "name": "Emma Lee"
          },
          "result_summary": "0 patient matches"
        },
        {
          "call_id": "01KSN58D6F0AERJFWB6DGHBHWR",
          "name": "verify_insurance",
          "args": {
            "member_id": "BCBS-884200",
            "payer": "Blue Cross Blue Shield PPO"
          },
          "result_summary": "insurance status: in_network (Blue Cross Blue Shield PPO)"
        },
        {
          "call_id": "01KSN58D6GR3MPSMPHAHEF84XY",
          "name": "lookup_policy",
          "args": {
            "topic": "insurance"
          },
          "result_summary": "3 policy snippets for insurance"
        },
        {
          "call_id": "01KSN58H3GVB8H2X7857EKZS11",
          "name": "find_slots",
          "args": {
            "discipline": "SLP",
            "preferences": "after school Tuesdays or Thursdays"
          },
          "result_summary": "4 matching slots; earliest 2026-04-29T09:00:00-07:00 with Maya Chen, MS CCC-SLP"
        },
        {
          "call_id": "01KSN58H3G9PGE0Z8N08VARAN5",
          "name": "lookup_policy",
          "args": {
            "topic": "scheduling"
          },
          "result_summary": "2 policy snippets for scheduling"
        },
        {
          "call_id": "01KSN58RYARRWYFZTC6PRM17SF",
          "name": "hold_slot",
          "args": {
            "patient_ref": "Emma Lee",
            "slot_id": "slot_slp_maya_2026_05_01_1530"
          },
          "result_summary": "created pending_review hold hold_01ksn58ryackmzhcndprrm42gm until 2026-05-27T17:16:16.010Z"
        },
        {
          "call_id": "01KSN58RYCDFZNRF25ZGAEKMNT",
          "name": "create_task",
          "args": {
            "assignee": "billing",
            "due": "2026-04-28",
            "notes": "New referral for Emma Lee (DOB 2018-09-04). Insurance verified active in-network: Blue Cross Blue Shield PPO, member ID BCBS-884200. Billing system flagged auth_required=true. Please initiate prior authorization for SLP evaluation before confirming the pending slot hold (slot_slp_maya_2026_05_01_1530, Thu May 1 at 3:30 PM with Maya Chen). Referral from Dr. Priya Nair at Northside Pediatrics. Parent contact: Daniel Lee, 555-0101, daniel.lee@example.com.",
            "title": "Prior auth required – Emma Lee, BCBS PPO SLP eval"
          },
          "result_summary": "created task task_01ksn58rycm8h7yzqk2v47acg9 for billing"
        },
        {
          "call_id": "01KSN594V6DCY5P8DEY7F4516E",
          "name": "draft_message",
          "args": {
            "body": "Dear Daniel,\n\nThank you for reaching out to Cedar Kids Therapy! We received the referral from Dr. Priya Nair at Northside Pediatrics for Emma's speech-language evaluation and we're excited to welcome her.\n\nWe have a potential appointment opening on Thursday, May 1st at 3:30 PM with Maya Chen, MS CCC-SLP, which aligns with your after-school Tuesday/Thursday preference. Our team is reviewing availability and insurance details — please note this is not yet a confirmed appointment.\n\nA member of our intake team will contact you shortly at 555-0101 to confirm the appointment, review insurance (Blue Cross Blue Shield PPO), and send over new patient paperwork.\n\nIf you have any questions in the meantime, please don't hesitate to reach us by phone or through our patient portal.\n\nWarm regards,\nCedar Kids Therapy",
            "channel": "email",
            "language": "en",
            "recipient": "Daniel Lee"
          },
          "result_summary": "created draft draft_01ksn594v6fmwewnar9a6xhz8c (email, en)"
        },
        {
          "call_id": "01KSN594V7VC9NV8CEE9J3Q2H8",
          "name": "create_task",
          "args": {
            "assignee": "intake",
            "due": "2026-04-28",
            "notes": "New fax referral received from Dr. Priya Nair (Northside Pediatrics) for Emma Lee (DOB 2018-09-04). Parent: Daniel Lee, 555-0101, daniel.lee@example.com. Discipline: SLP. Concern: articulation delay and reduced intelligibility. Insurance: BCBS PPO, member ID BCBS-884200 — verified in-network, active. Auth required (billing team tasked separately). Pending slot hold: Maya Chen, Thu May 1 at 3:30 PM (hold_01ksn58ryackmzhcndprrm42gm). Please: (1) call Daniel to introduce Cedar Kids and confirm interest, (2) send new patient intake forms, (3) coordinate with billing on auth status before confirming the slot, (4) attach referral PDF (referral_item_1.pdf) to patient chart once created.",
            "title": "New patient intake – Emma Lee, SLP eval referral"
          },
          "result_summary": "created task task_01ksn594v73sg1jkmcfavqhr11 for intake"
        }
      ]
    },
    {
      "item_id": "item_2",
      "classification": "safeguarding",
      "urgency": "P0",
      "requires_human_review": true,
      "extracted_intake": {
        "child_name": "Leo Gomez",
        "dob_or_age": "6 years old",
        "parent_contact": "Maria Gomez, 555-0102 (phone)",
        "discipline": [
          "SLP"
        ],
        "diagnosis_or_concern": "Speech therapy evaluation requested; also behavioral change (increased clinginess) noted by mother",
        "payer": null,
        "member_id": null
      },
      "missing_info": [
        "Date of birth (exact)",
        "Insurance payer and member ID",
        "Referring provider (if any)",
        "Any prior therapy history"
      ],
      "recommended_next_action": "Clinical lead must review the safeguarding disclosure immediately this morning, assess mandatory reporting obligations, and determine whether it is appropriate to proceed with scheduling before any further contact with the family.",
      "draft_reply": "Hi, this is Cedar Kids Therapy calling for Maria Gomez. We received your voicemail about Leo and want to thank you for reaching out to us. A member of our team will be calling you back shortly to follow up. If you need to reach us before then, please call our main office. Thank you.",
      "task_ids": [
        "task_01ksn58s3mgsx5dccdpfvghbay"
      ],
      "escalation": {
        "reason": "Mother's voicemail includes a disclosure that the child's father \"started getting rough with him during weekends.\" This language may indicate physical harm or unsafe caregiving of a 6-year-old child and requires immediate clinical lead review under safeguarding protocol.",
        "severity": "P0"
      },
      "decision_rationale": "The voicemail contains a potential abuse/unsafe caregiving disclosure (\"dad started getting rough with him\"), which meets the P0 safeguarding threshold under Cedar Kids policy regardless of any accompanying routine request. Leo is not an existing patient. No scheduling, clinical advice, or investigative guidance was provided; only a neutral acknowledgement was drafted. The clinical lead must review mandatory reporting obligations before any further action is taken on this referral.",
      "tools_called": [
        {
          "call_id": "01KSN58FH5FM605QQCTYXMNC5D",
          "name": "lookup_policy",
          "args": {
            "topic": "safeguarding"
          },
          "result_summary": "2 policy snippets for safeguarding"
        },
        {
          "call_id": "01KSN58FH6S70R2AGZX35B0YHV",
          "name": "search_patient",
          "args": {
            "name": "Leo Gomez"
          },
          "result_summary": "0 patient matches"
        },
        {
          "call_id": "01KSN58FH7QB77XY1RCFRD1797",
          "name": "escalate",
          "args": {
            "item_id": "item_2",
            "reason": "Mother's voicemail includes a disclosure that the child's father \"started getting rough with him during weekends.\" This language may indicate physical harm or unsafe caregiving of a 6-year-old child and requires immediate clinical lead review under safeguarding protocol.",
            "severity": "P0"
          },
          "result_summary": "created escalation esc_01ksn58fh63qz2mwjwm6k8jk8c severity P0"
        },
        {
          "call_id": "01KSN58S3NVN57SJCSM7DN91A4",
          "name": "create_task",
          "args": {
            "assignee": "clinical_lead",
            "due": "2026-04-28",
            "notes": "Mother Maria Gomez called (555-0102) on Sunday 4/27 requesting a speech eval for her 6-year-old son Leo. During the voicemail she stated: \"he has been more clingy since his dad started getting rough with him during weekends.\" This language may indicate physical harm or unsafe caregiving. Child is NOT currently a Cedar Kids patient. Escalation ID: esc_01ksn58fh63qz2mwjwm6k8jk8c. Clinical lead must review immediately and determine mandatory reporting obligations before any further scheduling or clinical contact occurs. Do NOT provide investigative advice to the family.",
            "title": "P0 SAFEGUARDING: Potential harm disclosure — Leo Gomez (age 6)"
          },
          "result_summary": "created task task_01ksn58s3mgsx5dccdpfvghbay for clinical_lead"
        },
        {
          "call_id": "01KSN58S3PGATMMVR6VC9J2005",
          "name": "draft_message",
          "args": {
            "body": "Hi, this is Cedar Kids Therapy calling for Maria Gomez. We received your voicemail about Leo and want to thank you for reaching out to us. A member of our team will be calling you back shortly to follow up. If you need to reach us before then, please call our main office. Thank you.",
            "channel": "phone",
            "language": "en",
            "recipient": "Maria Gomez"
          },
          "result_summary": "created draft draft_01ksn58s3p3h3r68xjzv3v6ad9 (phone, en)"
        }
      ]
    },
    {
      "item_id": "item_3",
      "classification": "new_referral",
      "urgency": "P2",
      "requires_human_review": true,
      "extracted_intake": {
        "child_name": "Owen Brooks",
        "dob_or_age": "2020-02-11",
        "parent_contact": "Rachel Brooks, 555-0103, rachel.brooks@example.com",
        "discipline": [
          "OT"
        ],
        "diagnosis_or_concern": "Sensory processing and feeding tolerance",
        "payer": "Kaiser HMO",
        "member_id": "KSR-4471"
      },
      "missing_info": [],
      "recommended_next_action": "Billing must complete an out-of-network benefits conversation with Rachel Brooks before any slot is held; intake should proceed with scheduling only after benefits are resolved.",
      "draft_reply": "Dear Rachel,\n\nThank you for reaching out to Cedar Kids Therapy! We received a referral from Dr. Helena Yu at Westside Pediatrics for an occupational therapy evaluation for Owen, and we're glad to connect with your family.\n\nBefore we can schedule an appointment, we want to make sure you have all the information you need regarding coverage. Owen's insurance plan (Kaiser HMO) is currently out-of-network with our practice, which means we'll need to have a quick benefits conversation with you to review your out-of-network benefits and discuss any potential costs before proceeding.\n\nA member of our billing team will be reaching out to you shortly at 555-0103 to walk you through this. If you have any questions in the meantime, please don't hesitate to contact us.\n\nWe look forward to speaking with you soon!\n\nWarm regards,\nCedar Kids Therapy",
      "task_ids": [
        "task_01ksn58thmnscvndr6k1qes9g2",
        "task_01ksn58thn2c693b1k21d30dez"
      ],
      "escalation": null,
      "decision_rationale": "This is a complete new OT referral with all intake fields present and no safeguarding concerns. Insurance verification confirmed Kaiser HMO is out-of-network, triggering the mandatory benefits conversation policy before any slot can be held. No slot was held; billing and intake tasks were created to ensure the correct sequence of steps is followed before scheduling proceeds.",
      "tools_called": [
        {
          "call_id": "01KSN58DA6BT0KE8BNQXXAPT0X",
          "name": "search_patient",
          "args": {
            "dob": "2020-02-11",
            "name": "Owen Brooks"
          },
          "result_summary": "0 patient matches"
        },
        {
          "call_id": "01KSN58DA7P5P1B169W7JFX2H0",
          "name": "verify_insurance",
          "args": {
            "member_id": "KSR-4471",
            "payer": "Kaiser HMO"
          },
          "result_summary": "insurance status: out_of_network (Kaiser HMO)"
        },
        {
          "call_id": "01KSN58DA7EH0QVRWJCXC0RZ18",
          "name": "lookup_policy",
          "args": {
            "topic": "insurance"
          },
          "result_summary": "3 policy snippets for insurance"
        },
        {
          "call_id": "01KSN58THMAPYBEB0HS7Z7EWVC",
          "name": "create_task",
          "args": {
            "assignee": "billing",
            "due": "2026-04-28",
            "notes": "New OT referral for Owen Brooks (DOB: 2020-02-11). Insurance verified as Kaiser HMO (Member ID: KSR-4471) — out-of-network. Per policy, a benefits conversation with the family (Rachel Brooks, 555-0103, rachel.brooks@example.com) must be completed before any appointment slot is held. Referral source: Dr. Helena Yu / Westside Pediatrics. Concern: sensory processing and feeding tolerance.",
            "title": "OON Benefits Conversation Required – Owen Brooks (Kaiser HMO)"
          },
          "result_summary": "created task task_01ksn58thmnscvndr6k1qes9g2 for billing"
        },
        {
          "call_id": "01KSN58THN1F02CTB910626SM9",
          "name": "create_task",
          "args": {
            "assignee": "intake",
            "due": "2026-04-28",
            "notes": "Referral received via fax from Dr. Helena Yu (Westside Pediatrics) for OT evaluation. Child: Owen Brooks, DOB 2020-02-11. Parent: Rachel Brooks, 555-0103, rachel.brooks@example.com. Concerns: sensory processing and feeding tolerance. Insurance: Kaiser HMO (out-of-network) — NO slot should be held until billing completes the OON benefits conversation. Family preference: morning slots. Once benefits are resolved, proceed with intake and scheduling.",
            "title": "New OT Referral – Owen Brooks – Pending OON Benefits Resolution"
          },
          "result_summary": "created task task_01ksn58thn2c693b1k21d30dez for intake"
        },
        {
          "call_id": "01KSN58THP4P455G4C8EGF6KS1",
          "name": "draft_message",
          "args": {
            "body": "Dear Rachel,\n\nThank you for reaching out to Cedar Kids Therapy! We received a referral from Dr. Helena Yu at Westside Pediatrics for an occupational therapy evaluation for Owen, and we're glad to connect with your family.\n\nBefore we can schedule an appointment, we want to make sure you have all the information you need regarding coverage. Owen's insurance plan (Kaiser HMO) is currently out-of-network with our practice, which means we'll need to have a quick benefits conversation with you to review your out-of-network benefits and discuss any potential costs before proceeding.\n\nA member of our billing team will be reaching out to you shortly at 555-0103 to walk you through this. If you have any questions in the meantime, please don't hesitate to contact us.\n\nWe look forward to speaking with you soon!\n\nWarm regards,\nCedar Kids Therapy",
            "channel": "email",
            "language": "en",
            "recipient": "Rachel Brooks"
          },
          "result_summary": "created draft draft_01ksn58thp2ms6swqahqedhw7x (email, en)"
        }
      ]
    },
    {
      "item_id": "item_4",
      "classification": "new_referral",
      "urgency": "P2",
      "requires_human_review": true,
      "extracted_intake": {
        "child_name": "Mateo Ramirez",
        "dob_or_age": "2019-03-15",
        "parent_contact": "Carla Mendez – carla.mendez@example.com – 555-0104",
        "discipline": [
          "PT"
        ],
        "diagnosis_or_concern": "Toe walking and frequent tripping – PT evaluation requested",
        "payer": "Aetna PPO",
        "member_id": "AET-9910"
      },
      "missing_info": [
        "No referral document attached — pediatrician referral mentioned but not provided",
        "Guardian identity requires verification: sender is Carla Mendez but existing patient record (pat_mateo_ramirez_jr) lists guardian as Sofia Ramirez",
        "Prior authorization for PT evaluation required by Aetna PPO — not yet obtained"
      ],
      "recommended_next_action": "Intake staff must verify that Carla Mendez is an authorized guardian for Mateo Ramirez (existing record shows different guardian) before confirming any appointment; billing should simultaneously pursue prior auth, and the pending-review hold on Wed Apr 29 1:00pm with Priya Shah PT should only be confirmed once both items are resolved.",
      "draft_reply": "Hi Carla,\n\nThank you for reaching out to Cedar Kids Therapy! We received your referral request for a physical therapy evaluation for Mateo.\n\nWe're reviewing availability and insurance details and a member of our team will be in touch shortly to confirm next steps, including scheduling and any authorization requirements.\n\nIn the meantime, if you have any questions, please don't hesitate to contact us at 555-0104.\n\nWarm regards,\nCedar Kids Therapy",
      "task_ids": [
        "task_01ksn59ryqtb4pgebpyk74tpvg",
        "task_01ksn59ryrkjkh1ekj99v709rk"
      ],
      "escalation": null,
      "decision_rationale": "This is a new PT referral with in-network Aetna PPO insurance verified active — however, prior authorization is required and not yet obtained. A patient record match was found (pat_mateo_ramirez_jr) but the listed guardian (Sofia Ramirez) does not match the sender (Carla Mendez), creating an identity verification flag that must be resolved before any PHI is shared or appointment confirmed. A pending-review hold was placed on the earliest available PT evaluation slot, but scheduling is blocked pending guardian verification and prior auth.",
      "tools_called": [
        {
          "call_id": "01KSN59A20BM69CMZ3ETZ2Q3HM",
          "name": "search_patient",
          "args": {
            "dob": "2019-03-15",
            "name": "Mateo Ramirez"
          },
          "result_summary": "1 patient match: Mateo Ramirez Jr. (2019-03-15)"
        },
        {
          "call_id": "01KSN59A21RG6YSNZNEN8P7491",
          "name": "verify_insurance",
          "args": {
            "member_id": "AET-9910",
            "payer": "Aetna PPO"
          },
          "result_summary": "insurance status: in_network (Aetna PPO)"
        },
        {
          "call_id": "01KSN59A227N5Z45EAN2DA31P9",
          "name": "lookup_policy",
          "args": {
            "topic": "insurance"
          },
          "result_summary": "3 policy snippets for insurance"
        },
        {
          "call_id": "01KSN59E0GPZN5VHY6EY313MJH",
          "name": "find_slots",
          "args": {
            "discipline": "PT"
          },
          "result_summary": "2 matching slots; earliest 2026-04-29T13:00:00-07:00 with Priya Shah, PT, DPT"
        },
        {
          "call_id": "01KSN59E0GY572NQ432PCHMHCD",
          "name": "lookup_policy",
          "args": {
            "topic": "scheduling"
          },
          "result_summary": "2 policy snippets for scheduling"
        },
        {
          "call_id": "01KSN59RYPPN5QCTWRAZBPEPBX",
          "name": "hold_slot",
          "args": {
            "patient_ref": "Mateo Ramirez (pat_mateo_ramirez_jr)",
            "slot_id": "slot_pt_priya_2026_04_29_1300"
          },
          "result_summary": "created pending_review hold hold_01ksn59ryn5xazfks3cvkwmfwx until 2026-05-27T17:16:48.789Z"
        },
        {
          "call_id": "01KSN59RYQ44NNYBCS60K6Z4DJ",
          "name": "create_task",
          "args": {
            "assignee": "intake",
            "due": "2026-04-28",
            "notes": "Referral email from Carla Mendez (carla.mendez@example.com, 555-0104) for Mateo Ramirez DOB 2019-03-15. Existing record pat_mateo_ramirez_jr lists guardian as Sofia Ramirez — name does not match. Confirm whether Carla Mendez is an authorized guardian/contact before confirming any appointment. Do not release protected patient info until identity is verified.",
            "title": "Verify guardian identity – Mateo Ramirez (item_4)"
          },
          "result_summary": "created task task_01ksn59ryqtb4pgebpyk74tpvg for intake"
        },
        {
          "call_id": "01KSN59RYR1DT9E47HWHWSKBP4",
          "name": "create_task",
          "args": {
            "assignee": "billing",
            "due": "2026-04-28",
            "notes": "Aetna PPO member ID AET-9910 verified in-network and active. However, auth_required=true per insurance verification. Please initiate or confirm prior authorization for PT evaluation (toe walking / frequent tripping) before slot_pt_priya_2026_04_29_1300 (Wed Apr 29 1:00pm, Priya Shah PT) is confirmed. Referral was reportedly sent by pediatrician — no referral document attached to email; may need to obtain from referring provider.",
            "title": "Confirm prior auth for PT eval – Mateo Ramirez (item_4)"
          },
          "result_summary": "created task task_01ksn59ryrkjkh1ekj99v709rk for billing"
        },
        {
          "call_id": "01KSN59XYC1AXNJXWMYAM7VP8N",
          "name": "draft_message",
          "args": {
            "body": "Hi Carla,\n\nThank you for reaching out to Cedar Kids Therapy! We received your referral request for a physical therapy evaluation for Mateo.\n\nWe're reviewing availability and insurance details and a member of our team will be in touch shortly to confirm next steps, including scheduling and any authorization requirements.\n\nIn the meantime, if you have any questions, please don't hesitate to contact us at 555-0104.\n\nWarm regards,\nCedar Kids Therapy",
            "channel": "email",
            "language": "en",
            "recipient": "Carla Mendez"
          },
          "result_summary": "created draft draft_01ksn59xycq619b4dcz7fgvn3y (email, en)"
        }
      ]
    },
    {
      "item_id": "item_5",
      "classification": "clinical_question",
      "urgency": "P2",
      "requires_human_review": true,
      "extracted_intake": {
        "child_name": "Ava Kim",
        "dob_or_age": "4 years old",
        "parent_contact": "Jordan Kim via parent portal",
        "discipline": [
          "SLP"
        ],
        "diagnosis_or_concern": "Parent asking whether inability to produce R sounds at age 4 is developmentally normal; seeking advice on whether to seek therapy or wait",
        "payer": null,
        "member_id": null
      },
      "missing_info": [
        "Date of birth (exact)",
        "Insurance/payer information",
        "Member ID",
        "Whether family is interested in scheduling an evaluation or screening"
      ],
      "recommended_next_action": "Clinical lead should review the developmental question about R sounds and either respond directly to Jordan Kim or approve a templated response; consider offering a free screening call to guide next steps.",
      "draft_reply": "Hi Jordan,\n\nThank you for reaching out about Ava! We're glad you felt comfortable asking.\n\nQuestions about speech sound development are a great reason to connect with one of our speech-language pathologists. Our clinical team will be in touch shortly to help point you in the right direction — whether that's a brief screening call, a full evaluation, or simply some guidance on next steps.\n\nWe appreciate your patience over the weekend and look forward to speaking with you soon.\n\nWarm regards,\nCedar Kids Therapy",
      "task_ids": [
        "task_01ksn59hecrenyaqxj0xrw2hgp"
      ],
      "escalation": null,
      "decision_rationale": "The parent is asking a clinical question about typical speech sound development (R sounds at age 4), which falls squarely under the clinical advice policy — front desk and automated systems must not respond with developmental guidance. No existing patient record was found for Ava Kim, so this is also a potential new family. The item is routed to the clinical lead for an appropriate response and a possible screening offer, which is the correct pathway rather than providing advice directly.",
      "tools_called": [
        {
          "call_id": "01KSN598R0QHJ6MQ47PQ896015",
          "name": "lookup_policy",
          "args": {
            "topic": "clinical_advice"
          },
          "result_summary": "2 policy snippets for clinical_advice"
        },
        {
          "call_id": "01KSN598R1HF02DTPTVZGHRX21",
          "name": "lookup_policy",
          "args": {
            "topic": "service_lines"
          },
          "result_summary": "2 policy snippets for service_lines"
        },
        {
          "call_id": "01KSN598R2A7FYWTSVEM80KVKS",
          "name": "search_patient",
          "args": {
            "name": "Ava Kim"
          },
          "result_summary": "0 patient matches"
        },
        {
          "call_id": "01KSN59HEC73209XHS847DNAYM",
          "name": "create_task",
          "args": {
            "assignee": "clinical_lead",
            "due": "2026-04-28",
            "notes": "Parent Jordan Kim (portal message, item_5) is asking whether it is developmentally normal for their 4-year-old daughter Ava to not yet produce R sounds, and whether they should wait until kindergarten. No patient record found (Ava Kim not in system). Per policy, front desk cannot advise — clinical lead should review and either respond directly or approve a templated response. Consider offering a free screening call if available.",
            "title": "Clinical question: R-sound development in 4-year-old (Ava Kim)"
          },
          "result_summary": "created task task_01ksn59hecrenyaqxj0xrw2hgp for clinical_lead"
        },
        {
          "call_id": "01KSN59HED1NK7X9J9M4MHBJDZ",
          "name": "draft_message",
          "args": {
            "body": "Hi Jordan,\n\nThank you for reaching out about Ava! We're glad you felt comfortable asking.\n\nQuestions about speech sound development are a great reason to connect with one of our speech-language pathologists. Our clinical team will be in touch shortly to help point you in the right direction — whether that's a brief screening call, a full evaluation, or simply some guidance on next steps.\n\nWe appreciate your patience over the weekend and look forward to speaking with you soon.\n\nWarm regards,\nCedar Kids Therapy",
            "channel": "portal",
            "recipient": "Jordan Kim"
          },
          "result_summary": "created draft draft_01ksn59hedyensej8kh5yrh1vx (portal, en)"
        }
      ]
    },
    {
      "item_id": "item_6",
      "classification": "missing_paperwork",
      "urgency": "P2",
      "requires_human_review": true,
      "extracted_intake": {
        "child_name": "Sam Taylor",
        "dob_or_age": null,
        "parent_contact": null,
        "discipline": [
          "SLP"
        ],
        "diagnosis_or_concern": "Speech delay (school-age child)",
        "payer": null,
        "member_id": null
      },
      "missing_info": [
        "Date of birth",
        "Parent/guardian name and contact information",
        "Insurance payer name",
        "Insurance member ID"
      ],
      "recommended_next_action": "Intake team should call Lakeview Pediatrics today to collect the four missing fields (DOB, parent/guardian contact, payer, and member ID) before any slot can be held or insurance verified.",
      "draft_reply": "Hello, this is Cedar Kids Therapy reaching out regarding a fax referral received from Dr. Omar Keene for patient Sam Taylor (SLP – speech delay). Thank you for thinking of us!\n\nTo proceed with scheduling an evaluation, we are missing several required fields from the referral:\n\n1. Child's date of birth\n2. Parent/guardian name and contact information (phone number and/or email)\n3. Insurance payer name\n4. Insurance member ID\n\nCould you please provide these details at your earliest convenience? Once we have the complete information, we will be happy to move forward with intake and get Sam scheduled. You can reach our intake team by phone or by faxing an updated referral form.\n\nThank you very much!",
      "task_ids": [
        "task_01ksn59zrtjca7y9vdr7e8edn0"
      ],
      "escalation": null,
      "decision_rationale": "This fax referral from Dr. Omar Keene at Lakeview Pediatrics is missing four critical fields — DOB, parent/guardian contact, insurance payer, and member ID — making it impossible to search the patient record fully, verify insurance, or hold any slot. No existing patient record was found under \"Sam Taylor\" without a DOB to narrow the match. The referral is classified as missing_paperwork at P2 (normal workflow) since there are no safeguarding, clinical urgency, or same-day operational triggers present.",
      "tools_called": [
        {
          "call_id": "01KSN59NB672N344J3TXVYM3WG",
          "name": "search_patient",
          "args": {
            "name": "Sam Taylor"
          },
          "result_summary": "0 patient matches"
        },
        {
          "call_id": "01KSN59NB7XRKB301WE3TVYTND",
          "name": "lookup_policy",
          "args": {
            "topic": "insurance"
          },
          "result_summary": "3 policy snippets for insurance"
        },
        {
          "call_id": "01KSN59NB86HS166FF7FXHHQBV",
          "name": "lookup_policy",
          "args": {
            "topic": "scheduling"
          },
          "result_summary": "2 policy snippets for scheduling"
        },
        {
          "call_id": "01KSN59ZRTREW97KC8GBR24RBG",
          "name": "create_task",
          "args": {
            "assignee": "intake",
            "due": "2026-04-28",
            "notes": "Fax referral received 2026-04-28 from Dr. Omar Keene at Lakeview Pediatrics for SLP (speech delay, school-age child). The following required fields are BLANK: DOB, parent/guardian name & contact, insurance payer, and member ID. No patient match found in the system. Contact Lakeview Pediatrics to obtain all missing information before any slot can be held. Referral attachment: referral_item_6.pdf.",
            "title": "Incomplete referral – Sam Taylor (Lakeview Pediatrics / Dr. Omar Keene)"
          },
          "result_summary": "created task task_01ksn59zrtjca7y9vdr7e8edn0 for intake"
        },
        {
          "call_id": "01KSN59ZRTCYGX506NKS4DRDVE",
          "name": "draft_message",
          "args": {
            "body": "Hello, this is Cedar Kids Therapy reaching out regarding a fax referral received from Dr. Omar Keene for patient Sam Taylor (SLP – speech delay). Thank you for thinking of us!\n\nTo proceed with scheduling an evaluation, we are missing several required fields from the referral:\n\n1. Child's date of birth\n2. Parent/guardian name and contact information (phone number and/or email)\n3. Insurance payer name\n4. Insurance member ID\n\nCould you please provide these details at your earliest convenience? Once we have the complete information, we will be happy to move forward with intake and get Sam scheduled. You can reach our intake team by phone or by faxing an updated referral form.\n\nThank you very much!",
            "channel": "phone",
            "recipient": "Lakeview Pediatrics / Dr. Omar Keene"
          },
          "result_summary": "created draft draft_01ksn59zrtqt61zm2aea4c3mrd (phone, en)"
        }
      ]
    },
    {
      "item_id": "item_7",
      "classification": "new_referral",
      "urgency": "P2",
      "requires_human_review": true,
      "extracted_intake": {
        "child_name": "Isabella Lopez",
        "dob_or_age": "Age 5",
        "parent_contact": "Ana Lopez – 555-0107",
        "discipline": [
          "SLP"
        ],
        "diagnosis_or_concern": "Speech evaluation requested",
        "payer": "Medicaid",
        "member_id": "MCD-55320"
      },
      "missing_info": [
        "Exact date of birth for Isabella Lopez (only age 5 provided)",
        "Completed intake paperwork / consent forms"
      ],
      "recommended_next_action": "Intake staff should review the Spanish-language draft phone message, call Ana Lopez at 555-0107 today to confirm the April 30 slot hold with Lucía Morales, collect Isabella's exact DOB, and initiate intake paperwork.",
      "draft_reply": "Hola Ana, le llamamos de Cedar Kids Therapy. Gracias por contactarnos para Isabella.\n\nHemos recibido su mensaje y nos complace informarle que el seguro Medicaid de Isabella está verificado y activo, sin costo de copago para usted.\n\nTenemos disponible una evaluación de habla con nuestra terapeuta bilingüe (español/inglés), Lucía Morales, MA CCC-SLP, el jueves 30 de abril a las 11:00 a.m. También hay disponibilidad el lunes 5 de mayo a las 2:00 p.m. si esa fecha le viene mejor.\n\nHemos reservado un lugar para Isabella de forma provisional mientras esperamos su confirmación. Por favor llámenos al número de la clínica para confirmar la cita o si tiene alguna pregunta.\n\nEstamos encantados de atender a Isabella. ¡Hasta pronto!",
      "task_ids": [
        "task_01ksn5ag4xezh122jvg7kazp1a"
      ],
      "escalation": null,
      "decision_rationale": "This is a straightforward new SLP referral for a 5-year-old Spanish-speaking child with active Medicaid (verified in-network, $0 copay, no auth required) — no safety concerns and no out-of-network complexity, so P2 is appropriate. Language access policy requires a Spanish-capable provider match; Lucía Morales (bilingual SLP) has an evaluation slot on April 30 which has been placed on a pending-review hold. The draft outbound message has been written in Spanish as required; exact DOB is missing and must be collected during intake confirmation call.",
      "tools_called": [
        {
          "call_id": "01KSN59ZCF0E0CDBG00KHYBHXN",
          "name": "search_patient",
          "args": {
            "name": "Isabella Lopez"
          },
          "result_summary": "0 patient matches"
        },
        {
          "call_id": "01KSN59ZCGZCYA0AQE2ST9Q88P",
          "name": "verify_insurance",
          "args": {
            "member_id": "MCD-55320",
            "payer": "Medicaid"
          },
          "result_summary": "insurance status: in_network (Medicaid)"
        },
        {
          "call_id": "01KSN59ZCGMS32R9G5S40D7JC9",
          "name": "lookup_policy",
          "args": {
            "topic": "insurance"
          },
          "result_summary": "3 policy snippets for insurance"
        },
        {
          "call_id": "01KSN59ZCGQ6ED45NJDG0JES7B",
          "name": "lookup_policy",
          "args": {
            "topic": "language_access"
          },
          "result_summary": "2 policy snippets for language_access"
        },
        {
          "call_id": "01KSN5A2ZJ241806JVK7TEX5X5",
          "name": "find_slots",
          "args": {
            "discipline": "SLP",
            "language": "es"
          },
          "result_summary": "2 matching slots; earliest 2026-04-30T11:00:00-07:00 with Lucia Morales, MA CCC-SLP"
        },
        {
          "call_id": "01KSN5AG4WD8X0KDF56DGDR17G",
          "name": "hold_slot",
          "args": {
            "patient_ref": "Isabella Lopez",
            "slot_id": "slot_slp_lucia_2026_04_30_1100"
          },
          "result_summary": "created pending_review hold hold_01ksn5ag4v2dq2hv0x686ddgyf until 2026-05-27T17:17:12.539Z"
        },
        {
          "call_id": "01KSN5AG4WGPETTH62BKGCYJBJ",
          "name": "draft_message",
          "args": {
            "body": "Hola Ana, le llamamos de Cedar Kids Therapy. Gracias por contactarnos para Isabella.\n\nHemos recibido su mensaje y nos complace informarle que el seguro Medicaid de Isabella está verificado y activo, sin costo de copago para usted.\n\nTenemos disponible una evaluación de habla con nuestra terapeuta bilingüe (español/inglés), Lucía Morales, MA CCC-SLP, el jueves 30 de abril a las 11:00 a.m. También hay disponibilidad el lunes 5 de mayo a las 2:00 p.m. si esa fecha le viene mejor.\n\nHemos reservado un lugar para Isabella de forma provisional mientras esperamos su confirmación. Por favor llámenos al número de la clínica para confirmar la cita o si tiene alguna pregunta.\n\nEstamos encantados de atender a Isabella. ¡Hasta pronto!",
            "channel": "phone",
            "language": "es",
            "recipient": "Ana Lopez"
          },
          "result_summary": "created draft draft_01ksn5ag4w9h4ap3knevnnkpbd (phone, es)"
        },
        {
          "call_id": "01KSN5AG4YVKG49R9TGRH87G1E",
          "name": "create_task",
          "args": {
            "assignee": "intake",
            "due": "2026-04-28",
            "notes": "New patient referral received via voicemail from Ana Lopez (mother). Child: Isabella Lopez, DOB/age approx. 5 years old (exact DOB not provided). Concern: speech evaluation. Payer: Medicaid MCD-55320 — verified active in-network, $0 copay, no auth required. Family requests Spanish-speaking provider. Slot held for evaluation with Lucía Morales, MA CCC-SLP (bilingual) on 2026-04-30 at 11:00 AM (slot_slp_lucia_2026_04_30_1100). Call Ana Lopez at 555-0107 to confirm appointment, collect exact DOB, and complete intake paperwork. Draft phone reply prepared in Spanish for review before outreach.",
            "title": "New SLP referral – Isabella Lopez (Spanish-speaking, age 5)"
          },
          "result_summary": "created task task_01ksn5ag4xezh122jvg7kazp1a for intake"
        }
      ]
    },
    {
      "item_id": "item_8",
      "classification": "scheduling",
      "urgency": "P1",
      "requires_human_review": true,
      "extracted_intake": {
        "child_name": "Noah Patel",
        "dob_or_age": "2017-11-02",
        "parent_contact": "Anita Patel — 555-0108 / anita.patel@example.com",
        "discipline": [
          "OT"
        ],
        "diagnosis_or_concern": null,
        "payer": null,
        "member_id": null
      },
      "missing_info": [],
      "recommended_next_action": "Front desk must immediately free the 3pm OT slot for Noah Patel (pat_noah_patel) and contact Anita Patel at 555-0108 or anita.patel@example.com to arrange a makeup appointment based on provider availability.",
      "draft_reply": "Hi Anita,\n\nWe're sorry to hear Noah isn't feeling well — we hope he feels better soon!\n\nWe've received your message about today's 3pm OT appointment and have flagged it for our team to handle right away. A staff member will reach out to you shortly at 555-0108 or via email to find a makeup time that works for your schedule.\n\nThank you for letting us know as soon as possible!\n\nWarm regards,\nCedar Kids Therapy",
      "task_ids": [
        "task_01ksn5ark10dsf2qzzw5sn1ztz"
      ],
      "escalation": {
        "reason": "Same-day cancellation of Noah Patel's 3pm OT appointment — provider slot needs to be freed and makeup scheduling must be arranged promptly.",
        "severity": "P1"
      },
      "decision_rationale": "This is a same-day cancellation request received Monday morning for a 3pm appointment, which triggers P1 per scheduling policy — the provider slot must be freed promptly and a makeup arranged. Noah Patel was confirmed as an active patient (pat_noah_patel) with guardian Anita Patel. No clinical or safeguarding concerns are present; this is purely an operational scheduling issue requiring immediate front desk action.",
      "tools_called": [
        {
          "call_id": "01KSN5ADHHFJADP6QXS95J36K0",
          "name": "search_patient",
          "args": {
            "dob": "2017-11-02",
            "name": "Noah Patel"
          },
          "result_summary": "1 patient match: Noah Patel (2017-11-02)"
        },
        {
          "call_id": "01KSN5ADHKAQ2X5H02Y8B954FC",
          "name": "lookup_policy",
          "args": {
            "topic": "cancellation"
          },
          "result_summary": "2 policy snippets for cancellation"
        },
        {
          "call_id": "01KSN5ARJZDMNXAFDFFPYZ8XJS",
          "name": "escalate",
          "args": {
            "item_id": "item_8",
            "reason": "Same-day cancellation of Noah Patel's 3pm OT appointment — provider slot needs to be freed and makeup scheduling must be arranged promptly.",
            "severity": "P1"
          },
          "result_summary": "created escalation esc_01ksn5arjzyzfhas53ctb1djgk severity P1"
        },
        {
          "call_id": "01KSN5ARK1NQ8DASN2T0JVDAPP",
          "name": "create_task",
          "args": {
            "assignee": "front_desk",
            "due": "2026-04-28",
            "notes": "Active patient Noah Patel (DOB: 2017-11-02, pat_noah_patel) is sick and cannot attend his 3pm OT appointment today. Guardian is Anita Patel, reachable at 555-0108 or anita.patel@example.com. Per policy, please: (1) mark the 3pm OT slot as cancelled/available ASAP, (2) coordinate a makeup appointment based on provider availability, and (3) contact Anita to confirm reschedule options.",
            "title": "Same-day OT cancellation — Noah Patel (today 3pm)"
          },
          "result_summary": "created task task_01ksn5ark10dsf2qzzw5sn1ztz for front_desk"
        },
        {
          "call_id": "01KSN5ARK1PP8X3185Q4BK7N2J",
          "name": "draft_message",
          "args": {
            "body": "Hi Anita,\n\nWe're sorry to hear Noah isn't feeling well — we hope he feels better soon!\n\nWe've received your message about today's 3pm OT appointment and have flagged it for our team to handle right away. A staff member will reach out to you shortly at 555-0108 or via email to find a makeup time that works for your schedule.\n\nThank you for letting us know as soon as possible!\n\nWarm regards,\nCedar Kids Therapy",
            "channel": "email",
            "recipient": "Anita Patel"
          },
          "result_summary": "created draft draft_01ksn5ark15yp2qw4twxg79534 (email, en)"
        }
      ]
    }
  ]
}
